kubemo/__init__.py
kubemo/__main__.py
kubemo/algorithm.py
kubemo/client.py
kubemo/errors.py
kubemo/inference.py
kubemo/protocol.py
kubemo/serialize.py
kubemo/server.py
kubemo/socket.py
kubemo/adaptor/__init__.py
kubemo/adaptor/arith.py
kubemo/adaptor/onnx.py
kubemo/adaptor/tensorflow.py
kubemo/adaptor/torch.py
kubemo-0.0.dev2.dist-info/LICENSE
kubemo-0.0.dev2.dist-info/METADATA
kubemo-0.0.dev2.dist-info/WHEEL
kubemo-0.0.dev2.dist-info/top_level.txt
kubemo-0.0.dev2.dist-info/RECORD
