Metadata-Version: 2.1
Name: kubemo
Version: 0.0.dev2
Summary: ML model deployment made simple
Home-page: https://github.com/kubemo/kubemo
Author: mivinci
Requires-Python: >=3.7
License-File: LICENSE
Requires-Dist: Pillow
Requires-Dist: numpy
Requires-Dist: requests
